jupyterlab_jupyterbook_navigation/__init__.py
jupyterlab_jupyterbook_navigation/_version.py
jupyterlab_jupyterbook_navigation-1.0.4.data/data/share/jupyter/labextensions/jupyterlab-jupyterbook-navigation/package.json
jupyterlab_jupyterbook_navigation-1.0.4.data/data/share/jupyter/labextensions/jupyterlab-jupyterbook-navigation/static/361.b92f1a2eed4322752cb6.js
jupyterlab_jupyterbook_navigation-1.0.4.data/data/share/jupyter/labextensions/jupyterlab-jupyterbook-navigation/static/361.b92f1a2eed4322752cb6.js.LICENSE.txt
jupyterlab_jupyterbook_navigation-1.0.4.data/data/share/jupyter/labextensions/jupyterlab-jupyterbook-navigation/static/413.e4f5bb2978b41ed03443.js
jupyterlab_jupyterbook_navigation-1.0.4.data/data/share/jupyter/labextensions/jupyterlab-jupyterbook-navigation/static/502.ac807e626db11cc98f49.js
jupyterlab_jupyterbook_navigation-1.0.4.data/data/share/jupyter/labextensions/jupyterlab-jupyterbook-navigation/static/remoteEntry.34fb7ba4de39f1b731a2.js
jupyterlab_jupyterbook_navigation-1.0.4.data/data/share/jupyter/labextensions/jupyterlab-jupyterbook-navigation/static/style.js
jupyterlab_jupyterbook_navigation-1.0.4.data/data/share/jupyter/labextensions/jupyterlab-jupyterbook-navigation/static/third-party-licenses.json
jupyterlab_jupyterbook_navigation-1.0.4.data/data/share/jupyter/labextensions/jupyterlab-jupyterbook-navigation/install.json
jupyterlab_jupyterbook_navigation-1.0.4.dist-info/METADATA
jupyterlab_jupyterbook_navigation-1.0.4.dist-info/WHEEL
jupyterlab_jupyterbook_navigation-1.0.4.dist-info/licenses/LICENSE
jupyterlab_jupyterbook_navigation-1.0.4.dist-info/RECORD
