Metadata-Version: 2.4
Name: jupyterlab_jupyterbook_navigation
Version: 1.0.4
Dynamic: Keywords
Summary: A JupyterLab extension that mimics jupyter-book chapter navigation on an un-built, cloned jupyter book in JupyterLab.
Project-URL: Homepage, https://github.com/ASFOpenSARlab/jupyterlab-jupyterbook-navigation
Project-URL: Bug Tracker, https://github.com/ASFOpenSARlab/jupyterlab-jupyterbook-navigation/issues
Project-URL: Repository, https://github.com/ASFOpenSARlab/jupyterlab-jupyterbook-navigation.git
Author-email: Alex Lewandowski <aflewandowski@alaska.edu>
License: BSD 3-Clause License
License-File: LICENSE
Classifier: Framework :: Jupyter
Classifier: Framework :: Jupyter :: JupyterLab
Classifier: Framework :: Jupyter :: JupyterLab :: 4
Classifier: Framework :: Jupyter :: JupyterLab :: Extensions
Classifier: Framework :: Jupyter :: JupyterLab :: Extensions :: Prebuilt
Classifier: License :: OSI Approved :: BSD License
Classifier: Programming Language :: Python
Classifier: Programming Language :: Python :: 3
Classifier: Programming Language :: Python :: 3.8
Classifier: Programming Language :: Python :: 3.9
Classifier: Programming Language :: Python :: 3.10
Classifier: Programming Language :: Python :: 3.11
Classifier: Programming Language :: Python :: 3.12
Requires-Python: >=3.8
Requires-Dist: jupyter-server-globbing
